tempoapiclient/__init__.py
tempoapiclient/client_v3.py
tempoapiclient/client_v4.py
tempoapiclient/rest_client.py
tempo_api_python_client-0.12.0.dist-info/LICENSE
tempo_api_python_client-0.12.0.dist-info/METADATA
tempo_api_python_client-0.12.0.dist-info/WHEEL
tempo_api_python_client-0.12.0.dist-info/top_level.txt
tempo_api_python_client-0.12.0.dist-info/RECORD
