Metadata-Version: 2.1
Name: tempo-api-python-client
Version: 0.12.0
Summary: Python bindings for Tempo (https://apidocs.tempo.io/)
Home-page: https://github.com/stanislavulrych/tempo-api-python-client
Author: Stanislav Ulrych
Author-email: stanislav.ulrych@gmail.com
Classifier: Programming Language :: Python :: 3
Classifier: License :: OSI Approved :: Apache Software License
Classifier: Operating System :: OS Independent
Requires-Python: >=3.10.14
License-File: LICENSE
Requires-Dist: requests
